LICENSE
README.md
setup.cfg
setup.py
FrameBench.egg-info/PKG-INFO
FrameBench.egg-info/SOURCES.txt
FrameBench.egg-info/dependency_links.txt
FrameBench.egg-info/entry_points.txt
FrameBench.egg-info/requires.txt
FrameBench.egg-info/top_level.txt
framebench/__init__.py
framebench/consts.py
framebench/list.py
framebench/main.py
framebench/proc_manager.py
framebench/run.py
framebench/test.py
framebench/models/config.py