Metadata-Version: 2.1
Name: FrameBench
Version: 2.0.0
Summary: A Benchmark for measuring frame timings from multiple cameras simultaneously
Home-page: https://github.com/kdvalin/framebench
Download-URL: https://github.com/kdvalin/framebench/archive/refs/tags/v1.0.1.tar.gz
Author: Keith Valin
Author-email: kvalin@redhat.com
License: GPL-3.0
Keywords: camera,webcam,framebench,test,benchmark,frame timings
Classifier: Development Status :: 5 - Production/Stable
Classifier: License :: OSI Approved :: GNU General Public License v3 (GPLv3)
Classifier: Operating System :: POSIX :: Linux
Classifier: Topic :: System :: Benchmark
Classifier: Programming Language :: Python :: 3
Classifier: Programming Language :: Python :: 3.10
Classifier: Programming Language :: Python :: 3.9
Classifier: Programming Language :: Python :: 3.8
License-File: LICENSE
